biolocsim/__init__.py
biolocsim/biolocsim.py
biolocsim/cli.py
biolocsim/core/__init__.py
biolocsim/core/base_config.py
biolocsim/core/ccp/__init__.py
biolocsim/core/ccp/ccp_generator.py
biolocsim/core/ccp/ccp_model.py
biolocsim/core/ccp/roi_generator.py
biolocsim/core/collision.py
biolocsim/core/microtubule.py
biolocsim/core/mitochondria.py
biolocsim/core/npc/__init__.py
biolocsim/core/npc/npc_generator.py
biolocsim/core/npc/npc_model.py
biolocsim/core/npc/nucleus_generator.py
biolocsim/core/render.py
biolocsim/utils/__init__.py
biolocsim/utils/geometry.py
biolocsim/utils/io.py
biolocsim/utils/visualize.py
biolocsim-0.3.0.dist-info/METADATA
biolocsim-0.3.0.dist-info/WHEEL
biolocsim-0.3.0.dist-info/entry_points.txt
biolocsim-0.3.0.dist-info/licenses/LICENSE
biolocsim-0.3.0.dist-info/RECORD
