Metadata-Version: 2.4
Name: biolocsim
Version: 0.3.0
Summary: A Python library for simulating SMLM point cloud data..
License: MIT
License-File: LICENSE
Author: Jixiang Ding
Author-email: dingsylv@gmail.com
Requires-Python: >=3.8,<4.0
Classifier: Development Status :: 2 - Pre-Alpha
Classifier: Intended Audience :: Developers
Classifier: License :: OSI Approved :: MIT License
Classifier: Natural Language :: English
Classifier: Programming Language :: Python :: 3
Classifier: Programming Language :: Python :: 3.8
Classifier: Programming Language :: Python :: 3.9
Classifier: Programming Language :: Python :: 3.10
Classifier: Programming Language :: Python :: 3.11
Classifier: Programming Language :: Python :: 3.12
Classifier: Programming Language :: Python :: 3.13
Classifier: Programming Language :: Python :: 3.14
Provides-Extra: dev
Provides-Extra: doc
Provides-Extra: test
Requires-Dist: black (>=21.5b2,<22.0) ; extra == "test"
Requires-Dist: bump2version (>=1.0.1,<2.0.0) ; extra == "dev"
Requires-Dist: click (==8.0.1)
Requires-Dist: h5py (>=3.1.0,<4.0.0) ; extra == "test" or extra == "dev"
Requires-Dist: isort (>=5.8.0,<6.0.0) ; extra == "test"
Requires-Dist: matplotlib (>=3.3.4,<4.0.0) ; extra == "test" or extra == "dev"
Requires-Dist: mkdocs (<=1.2.1) ; extra == "doc"
Requires-Dist: mkdocs-autorefs (<=0.2.1) ; extra == "doc"
Requires-Dist: mkdocs-include-markdown-plugin (<=1.0.0) ; extra == "doc"
Requires-Dist: mkdocs-material (<=6.1.7) ; extra == "doc"
Requires-Dist: mkdocstrings (<=0.15.2) ; extra == "doc"
Requires-Dist: numpy (>=1.20.1,<2.0.0) ; extra == "test" or extra == "dev"
Requires-Dist: opencv-python (>=4.5.1.48,<5.0.0.0) ; extra == "test" or extra == "dev"
Requires-Dist: pandas (>=1.2.1,<2.0.0) ; extra == "test" or extra == "dev"
Requires-Dist: pip (>=20.3.1,<21.0.0) ; extra == "dev"
Requires-Dist: pre-commit (>=2.12.0,<3.0.0) ; extra == "dev"
Requires-Dist: pytest (>=6.2.4,<7.0.0) ; extra == "test"
Requires-Dist: pytest-cov (>=2.12.0,<3.0.0) ; extra == "test"
Requires-Dist: scikit-image (>=0.18.1,<0.19.0) ; extra == "test" or extra == "dev"
Requires-Dist: scikit-learn (>=1.0.2,<2.0.0) ; extra == "test" or extra == "dev"
Requires-Dist: scipy (>=1.6.1,<2.0.0) ; extra == "test" or extra == "dev"
Requires-Dist: toml (>=0.10.2,<0.11.0) ; extra == "dev"
Requires-Dist: tox (>=3.20.1,<4.0.0) ; extra == "dev"
Requires-Dist: tqdm (>=4.55.1) ; extra == "test" or extra == "dev"
Requires-Dist: twine (>=3.3.0,<4.0.0) ; extra == "dev"
Requires-Dist: virtualenv (>=20.2.2,<21.0.0) ; extra == "dev"
Project-URL: Homepage, https://github.com/sylvanding/biolocsim
